aiolifx/__init__.py
aiolifx/__main__.py
aiolifx/aiolifx.py
aiolifx/connection.py
aiolifx/message.py
aiolifx/msgtypes.py
aiolifx/products.py
aiolifx/products_defs.py
aiolifx/unpack.py
aiolifx/update_products.py
aiolifx-1.2.1.dist-info/licenses/LICENSE.txt
aiolifx-1.2.1.dist-info/METADATA
aiolifx-1.2.1.dist-info/WHEEL
aiolifx-1.2.1.dist-info/entry_points.txt
aiolifx-1.2.1.dist-info/top_level.txt
aiolifx-1.2.1.dist-info/RECORD
