Metadata-Version: 2.4
Name: aiolifx
Version: 1.2.1
Summary: API for local communication with LIFX devices over a LAN with asyncio.
Home-page: http://github.com/aiolifx/aiolifx
Author: François Wautier
Author-email: francois@wautier.eu
License: MIT
Keywords: lifx,light,automation
Classifier: License :: OSI Approved :: MIT License
Classifier: Programming Language :: Python :: 3
Requires-Python: >=3.4
License-File: LICENSE.txt
Requires-Dist: async_timeout>=3.0.1
Requires-Dist: bitstring
Requires-Dist: ifaddr
Requires-Dist: click<8.2.0,>=8.1.0
Requires-Dist: InquirerPy<0.4.0,>=0.3.0
Dynamic: author
Dynamic: author-email
Dynamic: classifier
Dynamic: description
Dynamic: description-content-type
Dynamic: home-page
Dynamic: keywords
Dynamic: license
Dynamic: license-file
Dynamic: requires-dist
Dynamic: requires-python
Dynamic: summary
